dotpromptz_handlebars-0.1.8.dist-info/METADATA
dotpromptz_handlebars-0.1.8.dist-info/WHEEL
dotpromptz_handlebars-0.1.8.dist-info/licenses/LICENSE
handlebarrz/__init__.py
handlebarrz/_native.abi3.so
handlebarrz/_native.pyi
handlebarrz/py.typed
dotpromptz_handlebars-0.1.8.dist-info/RECORD
