Metadata-Version: 2.4
Name: dotpromptz-handlebars
Version: 0.1.8
Classifier: Development Status :: 3 - Alpha
Classifier: Programming Language :: Python :: 3
Classifier: Programming Language :: Python :: 3.10
Classifier: Programming Language :: Python :: 3.11
Classifier: Programming Language :: Python :: 3.12
Classifier: Programming Language :: Python :: 3.13
Classifier: Programming Language :: Python :: 3.14
Classifier: Programming Language :: Rust
Classifier: Topic :: Text Processing :: Markup
Requires-Dist: structlog>=25.2.0
License-File: LICENSE
Summary: Handlebars library for Python dotpromptz based on handlebars-rust.
Home-Page: https://github.com/google/dotprompt
Author-email: Yesudeep Mangalapilly <yesudeep@google.com>
Requires-Python: >=3.10
